csulb_mock_dataset/__init__.py
csulb_mock_dataset/cmp1.csv
csulb_mock_dataset/data.py
csulb_mock_student_dataset/__init__.py
csulb_mock_student_dataset/cmp1.csv
csulb_mock_student_dataset/data.py
files/__init__.py
files/data.py
csulb_mock_student_dataset-0.2.1.dist-info/METADATA
csulb_mock_student_dataset-0.2.1.dist-info/WHEEL
csulb_mock_student_dataset-0.2.1.dist-info/top_level.txt
csulb_mock_student_dataset-0.2.1.dist-info/RECORD
